mindustry_settings/__main__.py
mindustry_settings/data_input_stream.py
mindustry_settings/data_output_stream.py
mindustry_settings/settings.py
mindustry_settings-0.2.0.dist-info/METADATA
mindustry_settings-0.2.0.dist-info/WHEEL
mindustry_settings-0.2.0.dist-info/top_level.txt
mindustry_settings-0.2.0.dist-info/RECORD
