Metadata-Version: 2.4
Name: mindustry-settings
Version: 0.2.0
Summary: A library to read and write from/to Mindustry settings binaries.
Author-email: Lett <lett@mail.lettsn.org>
License-Expression: GPL-3.0
Project-URL: Homepage, https://github.com/BnDLett/mindustry-settings
Project-URL: Issues, https://github.com/BnDLett/mindustry-settings/issues
Classifier: Programming Language :: Python :: 3
Classifier: Operating System :: OS Independent
Requires-Python: >=3.9
